# CodeObject字节码

我们定义一个函数`f`，然后查看一下它的CodeObject对象

```python
def f():
    pass

code = f.__code__
print(code)

# <code object f at 0x000002112C32CF50, file "xxx.py", line 1>
```

实际上，所有写下来的代码都被编译成为了CodeObject交给虚拟机去执行了。

## CodeObject的属性

### 二进制字节码

```python
print(code.co_code)

#b'd\x00S\x00'
```

`co_code`是co真正的byte code二进制编码，我们通常使用`dis`这个模块讲这些二进制编码翻译成程序员能够看懂的语言。

```python
dis.dis('''
def f():
    pass
''')

#   2           0 LOAD_CONST               0 (<code object f at 0x00000242B442ECE0, file "<dis>", line 2>)
#               2 LOAD_CONST               1 ('f')
#               4 MAKE_FUNCTION            0
#               6 STORE_NAME               0 (f)
#               8 LOAD_CONST               2 (None)
#              10 RETURN_VALUE
# 
# Disassembly of <code object f at 0x00000242B442ECE0, file "<dis>", line 2>:
#   3           0 LOAD_CONST               0 (None)
#               2 RETURN_VALUE
```

怎么阅读`dis`的输出我们之后会讲。

### 不直接参与代码运行的元数据

```python
print(code.co_name)
print(code.co_filename)
print(code.co_lnotab)

# f
# D:\pythonProject\魔术方法\1.基础.py
# b'\x00\x01'
```

这三个输出是和实际的代码运行没有关系的数据，保存了这段代码的名字、文件名、代码在文件中的行数。其中行数是经过一些算法进行压缩后的二进制数据。

### run time使用的信息

```python
print(code.co_flags)
print(code.co_stacksize)

# 67
# 1
```

这两个属性都是虚拟机在运行这段co的时候需要用到的数据。`co_stacksize`就是这个co所需要的栈的空间有多大；`co_flags`是一个bitmap，用来判断这段code有没有什么特别的属性，比如是否有*args、**kwargs、是否是个generator、coroutine……通过这些flags的判断，python在运行这段代码的过程中会有不同的行为。

### 参数数量



```python
print(code.co_argcount)
print(code.co_posonlyargcount)
print(code.co_kwonlyargcount)
```

这三个属性是关于输入参数的数量的，这些属性决定了python在向函数中传参数的时候怎么处理这些参数，也是python进行函数重载的基础。

在此之前我们先需要理解什么是positional only argment和keyword only argment

```python
def f(a, b=3, *args, **kwargs):
    pass

code = f.__code__

print(code.co_argcount)
print(code.co_posonlyargcount)
print(code.co_kwonlyargcount)

# 2
# 0
# 0
```

将之前的函数做一些变形后我们可以看到这些参数既不是posonly的也不是kwonly的。我们运行这样的代码就会报错：

```python
def f(a, b=3, /, *args, **kwargs):
    pass

code = f.__code__
print(code.co_argcount)
print(code.co_posonlyargcount)
print(code.co_kwonlyargcount)

f(a = 1)

# 2
# 2
# 0
# TypeError: f() missing 1 required positional argument: 'a'
```

```python
def f(a, *,b=3, **kwargs):
    pass

code = f.__code__
print(code.co_argcount)
print(code.co_posonlyargcount)
print(code.co_kwonlyargcount)

f(1, 1)

# 1
# 0
# 1
# Traceback (most recent call last):
#   File "D:\pythonProject\魔术方法\1.基础.py", line 10, in <module>
#     f(1, 1)
# TypeError: f() takes 1 positional argument but 2 were given
```

* co_argcount：除了posobly和kwonly以外的参数数量
* co_posonlyargcount：只能位置传参的参数数量
* co_kwonlyargcount：只能关键字传参的参数数量

### byte code的设计需求

```python
def f(a):
    b = a
    return b
```

我们在进行代码编写的时候经常需要写一些非常长的变量名并且这些变量名会出现很多次，如果需要将这些变量名转换为二进制字节码的话就非常浪费空间。同时因为变量保存的都是python object，所以还需要维护一个变量和对象之间的映射。

所以解决方法是维护一个数组，将新的变量指定一个脚标，这样时间和空间上都有了非常大的优化。以上代码的字节码就是将第0个位置上的数据保存到第1个位置上去：

```python
Disassembly of <code object f at 0x00000177A3E4EEF0, file "<dis>", line 2>:
  3           0 LOAD_FAST                0 (a)
              2 STORE_FAST               1 (b)

  4           4 LOAD_FAST                1 (b)
              6 RETURN_VALUE
```

同时我们维护一个变量名称的数组，和变量保持index一致。

### 变量

```python
import dis


def f(a):
    b = a
    c = a.attr
    import math as m
    return b

code = f.__code__

print(f'nlocals：{code.co_nlocals}')

print(f'varnames：{code.co_varnames}')
print(f'names：{code.co_names}')
print(f'cellvars：{code.co_cellvars}')
print(f'freevars：{code.co_freevars}')

print(f'consts：{code.co_consts}')

dis.dis(f)

#   5           0 LOAD_FAST                0 (a)
#               2 STORE_FAST               1 (b)
#
#   6           4 LOAD_FAST                1 (b)
#               6 RETURN_VALUE

# nlocals：4
# varnames：('a', 'b', 'c', 'm')
# names：('attr', 'math')
# cellvars：()
# freevars：()
# consts：(None, 0)

dis.dis(f)

  5           0 LOAD_FAST                0 (a)
              2 STORE_FAST               1 (b)

  6           4 LOAD_FAST                0 (a)
              6 LOAD_ATTR                0 (attr)
              8 STORE_FAST               2 (c)

  7          10 LOAD_CONST               1 (0)
             12 LOAD_CONST               0 (None)
             14 IMPORT_NAME              1 (math)
             16 STORE_FAST               3 (m)

  8          18 LOAD_FAST                1 (b)
             20 RETURN_VALUE
```

local variable是局部变量，包括了传进函数的所有参数以及只在这个函数中用到的变量，这个例子中显然是a, b。`co_varnames`是这些变量的名称，`co_nlocals`是这些变量的数量，也就是`co_varnames`的大小。

```
  5           0 LOAD_FAST                0 (a)
              2 STORE_FAST               1 (b)

  6           4 LOAD_FAST                1 (b)
              6 RETURN_VALUE
```

实际的字节码里是没有(a)和(b)的，这时dis帮助我们理解写上去的。`LOAD_FAST	0`中0的含义是`co_varnames`中index为0的位置的变量名。

`co_names`和`co_name`是完全没有关系的属性，`co_name`是CodeObject表示这段代码名称的属性，`co_names`保存了除了`co_varnames`、`co_cellvars`和`co_freevars`之外的其他所有string。注意，`import math as m`中的math和m被保存在了不同的位置，m作为代表了一个python object的变量被保存在`co_varnames`中，math只是作为string被保存在`co_names`中。

**`co_cellvars`和`co_freevars`是为了完成闭包而设计的，意味着告诉函数在这里的变量进行赋值、读取操作的时候要进行一些特殊的操作。**`co_cellvars`的含义是这里的变量还会在其他的scope中用到，`co_freevars`的含义是这里的变量是从其他的scope中来的。

```python
import dis


def f():
    d = {}
    def g():
        d['a'] = 1
    return g

code = f.__code__

print(f'nlocals：{code.co_nlocals}')

print(f'varnames：{code.co_varnames}')
print(f'names：{code.co_names}')
print(f'cellvars：{code.co_cellvars}')
print(f'freevars：{code.co_freevars}')

print(f'consts：{code.co_consts}')

dis.dis(f)

# nlocals：1
# varnames：('g',)
# names：()
# cellvars：('d',)
# freevars：()
# consts：(None, <code object g at 0x00000140CE55CD40, file "D:\xxx.py", line 6>, 'f.<locals>.g')
```

`cellvars：('d',)`意味着`d`这个变量不仅在`f`函数本身使用了，还在其他的scope中使用了，如果`f`中没有使用`d`的话`d`就会是一个varnames而不是cellvars。实际上python在这里将这个object b变成了一个cell object，相当于封装成了一个指针或者引用供不同的scope去获取。

```python
import dis


def f():
    d = {}
    def g():
        d['a'] = 1
    return g

code = f().__code__

print(f'nlocals：{code.co_nlocals}')

print(f'varnames：{code.co_varnames}')
print(f'names：{code.co_names}')
print(f'cellvars：{code.co_cellvars}')
print(f'freevars：{code.co_freevars}')

print(f'consts：{code.co_consts}')

# nlocals：0
# varnames：()
# names：()
# cellvars：()
# freevars：('d',)
# consts：(None, 1, 'a')
```

因为`f()`直接返回了`g`，所以我们可以打印`g`的CodeObject的属性，可以看到`d`在`co_freevars`中。

```python
def f():
    d = {}
    def g():
        d['a'] = 1
    return g  

  5           0 BUILD_MAP                0
              2 STORE_DEREF              0 (d)
        
def f():
    d = {}
    def g():
        #d['a'] = 1
        pass
    return g

  5           0 BUILD_MAP                0
              2 STORE_FAST               0 (d)
```

从字节码中也可以看出不同，`STORE_FAST`是对`varnames`的操作，而`STORE_DEREF`是针对`cell object`的操作。

`co_consts`中保存的是python object。函数中出现的所有常量值都会保存在`co_consts`中，None永远保存在`co_consts`中。