# 建立一个class的底层过程

当我们定义一个类的时候发生了什么？我们先看一下字节码：

```python
class A:
    name = 'name'
    def fun(self):
        print(1)
```

输出如下：

```python
# part1
  1           0 LOAD_BUILD_CLASS
              2 LOAD_CONST               0 (<code object A at 0x00000228AF81F3C0, file "<dis>", line 1>)
              4 LOAD_CONST               1 ('A')
              6 MAKE_FUNCTION            0
              8 LOAD_CONST               1 ('A')
             10 CALL_FUNCTION            2
             12 STORE_NAME               0 (A)
             14 LOAD_CONST               2 (None)
             16 RETURN_VALUE

# part2
Disassembly of <code object A at 0x00000228AF81F3C0, file "<dis>", line 1>:
  1           0 LOAD_NAME                0 (__name__)
              2 STORE_NAME               1 (__module__)
              4 LOAD_CONST               0 ('A')
              6 STORE_NAME               2 (__qualname__)

  2           8 LOAD_CONST               1 ('name')
             10 STORE_NAME               3 (name)

  3          12 LOAD_CONST               2 (<code object fun at 0x00000228AF81F310, file "<dis>", line 3>)
             14 LOAD_CONST               3 ('A.fun')
             16 MAKE_FUNCTION            0
             18 STORE_NAME               4 (fun)
             20 LOAD_CONST               4 (None)
             22 RETURN_VALUE

# part3
Disassembly of <code object fun at 0x00000228AF81F310, file "<dis>", line 3>:
  4           0 LOAD_GLOBAL              0 (print)
              2 LOAD_CONST               1 (1)
              4 CALL_FUNCTION            1
              6 POP_TOP
              8 LOAD_CONST               0 (None)
             10 RETURN_VALUE
```

我们可以看到`part3`在class内部定义的函数`fun`和在class外定义的函数没有区别，都是一个code object对象。`part2`部分的内容本质上是`class A:`里面的内容单独拿出来作为一段程序去处理了。

根据dis的编译的字节码我们可以知道0 2 4 6做了两件事：`__module__ = __name__ `，`__qualname__ = 'A'`。8 10做了`name = 'name'`。

12~22做了一个函数，名称是`A.fun`，根据code object fun做了这个函数之后保存在了`fun`这个变量里。

我们看向`part1`：

```python
# part1
  1           0 LOAD_BUILD_CLASS
              2 LOAD_CONST               0 (<code object A at 0x00000228AF81F3C0, file "<dis>", line 1>)
              4 LOAD_CONST               1 ('A')
              6 MAKE_FUNCTION            0
              8 LOAD_CONST               1 ('A')
             10 CALL_FUNCTION            2
             12 STORE_NAME               0 (A)
             14 LOAD_CONST               2 (None)
             16 RETURN_VALUE
```

在这里我们先使用`LOAD_BUILD_CLASS`将`builtins.__build_class__()`函数push进栈中。2 4 6做了一个叫A的函数，也就是对应源代码中的2 3 4行。然后CALL_FUNCTION使用了`builtins.__build_class__()`将返回值保存到了`A`这个变量中。这个返回值是一个type。

## 总结

实际上就是一个命名空间运行了class中的code block，然后将所有的私有变量放进了class的`__dict__`中。class中的函数和正常的函数没有本质上的区别。

# MRO：方法解析顺序

对于支持继承的编程语言来说，其方法（属性）可能定义在当前类，也可能来自于基类，所以在方法调用时就需要对当前类和基类进行搜索以确定方法所在的位置。而搜索的顺序就是所谓的「方法解析顺序」（Method Resolution Order，或MRO）。对于只支持单继承的语言来说，MRO 一般比较简单；而对于 Python 这种支持多继承的语言来说，MRO 就复杂很多。

Python 2.3 的新式类的[ C3 算法](https://en.wikipedia.org/wiki/C3_linearization)，它也是 Python 3 唯一支持的方式。实际上就是将继承的父类做一个线性化，没有在自身找到方法和属性后向上寻找。

C3算法保证了以下3点：

1. 保持继承[拓扑图](https://link.zhihu.com/?target=https%3A//zh.wikipedia.org/w/index.php%3Ftitle%3D%E6%8B%93%E6%89%91%E5%9B%BE%26action%3Dedit%26redlink%3D1)的一致性：个集合上的一个偏序得到该集合上的一个全序，这个操作称之为拓扑排序。
2. 局部优先顺序：`M(A, B)`则M会先在A中寻找，`N(M)`使得N也会保证这个特性。
3. 单调性：优先从自己的直接父类中寻找方法和属性

```python
def c3MRO(cls):
    if cls is object:
        # 讨论假设顶层基类为object，递归终止
        return [object]

    # 构造C3-MRO算法的总式，递归开始
    mergeList = [c3MRO(baseCls) for baseCls in cls.__bases__]
    mergeList.append(list(cls.__bases__))
    mro = [cls] + merge(mergeList)
    return mro


def merge(inLists):
    if not inLists:
        # 若合并的内容为空，返回空list
        # 配合下文的排除空list操作，递归终止
        return []

    # 遍历要合并的mro
    for mroList in inLists:
        # 取head
        head = mroList[0]
        # 遍历要合并的mro（与外一层相同），检查尾中是否有head
        ### 此处也遍历了被取head的mro，严格地来说不符合标准算法实现
        ### 但按照多继承中地基础规则（一个类只能被继承一次），
        ### head不可能在自己地尾中，无影响，若标准实现，反而增加开销
        for cmpList in inLists[inLists.index(mroList) + 1:]:
            if head in cmpList[1:]:
                break
        else:
            # 筛选出好head
            nextList = []
            for mergeItem in inLists:
                if head in mergeItem:
                    mergeItem.remove(head)
                if mergeItem:
                    # 排除空list
                    nextList.append(mergeItem)
            # 递归开始
            return [head] + merge(nextList)
    else:
        # 无好head，引发类型错误
        raise TypeError
```

# class中的self是什么

我们在class机制中降到了class中的函数和普通的函数没有什么区别，但是显然我们在传参的时候有一个默认的self不需要传入但是实际上class中的方法必不可少。

```python
class A:
    def f(self, data):
        print(self.name)
        print(data)


o = A()

print(A.f)
print(o.f)
print(o.__dict__)

# <function A.f at 0x0000021E47D61240>
# <bound method A.f of <__main__.A object at 0x0000021E47FB09D0>>
# {}
```

`A.f`就是一个普通的function object，而`o.f`是一个bound method（函数上绑定了一个对象，这个对象就是o），是一个method object。

`o.f`中的f首先会在o的属性方法中寻找，其实这里是找不到的，所以会去o的type：A中寻找。找到f后并不是直接返回f而是返回descriptor get的返回值，是一个绑定了对象o的method object。所以在调用的时候只需要传入self之后的args。

```python
class A:
    pass

def f(self, data):
    print(self.name)
    print(data)


o = A()
o.f = f
print(o.__dict__)
o.f("Hello")

# {'f': <function f at 0x000002011F0EA950>}
# TypeError: f() missing 1 required positional argument: 'data'
```

当我们动态绑定一个function到对象o上的时候就会发现我们需要手动指定self参数。

## 总结

class中定义的函数没有什么神奇的，它就是一个普通的函数存储在class的`__dict__`中。当我们从对象中access对象的attribute的时候class本身的descriptor get函数将这个普通的function object变成了一个method object并且返回了。

# metaclass

```python
class M(type):
    def __new__(cls, name, bases, attrs):
        return type.__new__(cls, name, bases, attrs)

class A():
    pass

B = type("B", (), {})
```

我们可以静态建立一个class也可以动态使用type建立一个class，两种建立方式是等价的。由于type的建立直接调用了c中的代码，所以我们希望能有一种在python层面可控的方式等价使用`B = type("B", (), {})`中的type。这就是元类metaclass建立的初衷。

```python
class M(type):
    def __new__(cls, name, bases, attrs):
        return type.__new__(cls, name, bases, attrs)

class A(metaclass=M):
    pass

B = M("B", (), {})
o = A()
```

两种建立方式是等价的，`o = A()`实际上是调用了class A的`__new__`方法和`__init__`方法，`B = M("B", (), {})`实际上也是调用了class M的`__new__`方法和`__init__`。所以我们可以重写这些方法来获取一些灵活性。

```python
class M(type):
    def __new__(cls, name, bases, attrs):
        print(cls, name, bases, attrs)
        return type.__new__(cls, name, bases, attrs)

class A(metaclass=M):
    pass

B = M("B", (), {})

o = A()

# <class '__main__.M'> A () {'__module__': '__main__', '__qualname__': 'A'}
# <class '__main__.M'> B () {}
```

因此我们可以利用metaclass来实现单例模式。
